termaconfig/__init__.py
termaconfig/configtables.py
termaconfig/errortree.py
termaconfig/exceptions.py
termaconfig/parser.py
termaconfig/utils.py
termaconfig-1.0.1.dist-info/LICENSE
termaconfig-1.0.1.dist-info/METADATA
termaconfig-1.0.1.dist-info/WHEEL
termaconfig-1.0.1.dist-info/RECORD
