Metadata-Version: 2.3
Name: termaconfig
Version: 1.0.1
Summary: Create pretty representations of your configs
License: GPL-3.0
Author: Zentheon
Author-email: zentheon@mailbox.org
Requires-Python: >=3.12,<4.0
Classifier: License :: OSI Approved :: GNU General Public License v3 (GPLv3)
Classifier: Programming Language :: Python :: 3
Classifier: Programming Language :: Python :: 3.12
Classifier: Programming Language :: Python :: 3.13
Requires-Dist: configobj (>=5.0.9,<6.0.0)
Requires-Dist: printree (>=0.2.1,<0.3.0)
Requires-Dist: terminaltables3 (>=4.0.0,<5.0.0)
Project-URL: Homepage, https://github.com/zentheon/termaconfig
